sckg/__init__.py
sckg/buildtrie.py
sckg/cli.py
sckg/graph.py
sckg/sckg.py
sckg-0.1.7.dist-info/AUTHORS.rst
sckg-0.1.7.dist-info/LICENSE
sckg-0.1.7.dist-info/METADATA
sckg-0.1.7.dist-info/WHEEL
sckg-0.1.7.dist-info/entry_points.txt
sckg-0.1.7.dist-info/top_level.txt
sckg-0.1.7.dist-info/RECORD
