Metadata-Version: 2.1
Name: sckg
Version: 0.1.7
Summary: A Software Concept Knowledge Graph
Home-page: https://github.com/FudanSELab/sckg
Author: Software Concept Knowledge Graph
Author-email: lmwtclmwtc@outlook.com
License: MIT license
Keywords: sckg
Platform: UNKNOWN
Classifier: Development Status :: 2 - Pre-Alpha
Classifier: Intended Audience :: Developers
Classifier: License :: OSI Approved :: MIT License
Classifier: Natural Language :: English
Classifier: Programming Language :: Python :: 3
Classifier: Programming Language :: Python :: 3.6
Classifier: Programming Language :: Python :: 3.7
Classifier: Programming Language :: Python :: 3.8
Requires-Python: >=3.6
License-File: LICENSE
License-File: AUTHORS.rst
Requires-Dist: Click (>=7.0)
Requires-Dist: kgdt (>=0.4.1)
Requires-Dist: pygtrie
Requires-Dist: tqdm
